README.rst
setup.py
warcsigner/__init__.py
warcsigner/gzipmeta.py
warcsigner/warcsigner.py
warcsigner.egg-info/PKG-INFO
warcsigner.egg-info/SOURCES.txt
warcsigner.egg-info/dependency_links.txt
warcsigner.egg-info/entry_points.txt
warcsigner.egg-info/not-zip-safe
warcsigner.egg-info/requires.txt
warcsigner.egg-info/top_level.txt