Metadata-Version: 1.1
Name: warcsigner
Version: 0.3.1
Summary: Tools for signing and verifying WARC files
Home-page: https://github.com/ikreymer/warcsigner
Author: Ilya Kreymer
Author-email: ikreymer@gmail.com
License: MIT
Platform: UNKNOWN
Classifier: Development Status :: 4 - Beta
Classifier: Programming Language :: Python :: 2.6
Classifier: Programming Language :: Python :: 2.7
Classifier: Topic :: Software Development :: Libraries :: Python Modules
Classifier: Topic :: System :: Archiving
Classifier: Topic :: System :: Archiving :: Backup
Classifier: Topic :: Utilities
Provides: warcsigner
